<?xml version="1.0" encoding="utf-8"?>
<Defs>

    <ThingDef ParentName="BuildingBase">
        <defName>AC_SleeveIncubator</defName>
        <label>sleeve incubator</label>
        <description>An ultra-tech vat tank connected to advanced life support systems and an AI core. Used by the rich 1% on ultra-tech worlds and less trustworthy individuals on rimworlds to grow custom sleeves, the sleeve incubator is capable of growing any human body one can imagine.</description>
		<thingClass>AlteredCarbon.Building_SleeveGrower</thingClass>
		<tickerType>Normal</tickerType>
		<drawerType>RealtimeOnly</drawerType>
        <graphicData>
            <texPath>Things/Building/Misc/SleeveGrowingVatBottom</texPath>
            <graphicClass>Graphic_Single</graphicClass>
            <drawSize>(6,6)</drawSize>
            <shaderType>CutoutComplex</shaderType>
            <damageData>
                <cornerTL>Damage/Corner</cornerTL>
                <cornerTR>Damage/Corner</cornerTR>
                <cornerBL>Damage/Corner</cornerBL>
                <cornerBR>Damage/Corner</cornerBR>
            </damageData>
        </graphicData>
        <costList>
            <Steel>250</Steel>
            <ComponentIndustrial>5</ComponentIndustrial>
        </costList>
        <altitudeLayer>Building</altitudeLayer>
        <neverMultiSelect>true</neverMultiSelect>
        <uiIconScale>1.2</uiIconScale>
        <useHitPoints>True</useHitPoints>
        <statBases>
            <WorkToBuild>8000</WorkToBuild>
            <MaxHitPoints>10000</MaxHitPoints>
            <Flammability>1.0</Flammability>
            <Beauty>-5</Beauty>
        </statBases>
		<designationCategory>Misc</designationCategory>
        <size>(5,5)</size>
        <techLevel>Ultra</techLevel>
        <passability>Impassable</passability>
        <pathCost>70</pathCost>
		<blockWind>true</blockWind>
        <surfaceType>Item</surfaceType>
		<researchPrerequisites>
		  <li>AC_SleeveProduction</li>
		</researchPrerequisites>
		<placeWorkers>
			<li>PlaceWorker_FuelingPort</li>
		</placeWorkers>
        <comps>
            <li Class="CompProperties_Power">
                <compClass>CompPowerTrader</compClass>
                <shortCircuitInRain>true</shortCircuitInRain>
                <basePowerConsumption>4500</basePowerConsumption>
            </li>
			<li Class="CompProperties_Refuelable">
				<consumeFuelOnlyWhenUsed>true</consumeFuelOnlyWhenUsed>
				<targetFuelLevelConfigurable>true</targetFuelLevelConfigurable>
				<fuelCapacity>400.0</fuelCapacity>
				<fuelConsumptionPerTickInRain>0</fuelConsumptionPerTickInRain>
				<fuelFilter>
					<thingDefs>
						<li>Meat_Human</li>
					</thingDefs>
				</fuelFilter>
				<initialFuelPercent>1</initialFuelPercent>
				<showAllowAutoRefuelToggle>true</showAllowAutoRefuelToggle>
				<showFuelGizmo>true</showFuelGizmo>
			</li>
			<li Class="CompProperties_Glower">
				<glowRadius>6</glowRadius>
				<glowColor>(96,161,153,0)</glowColor>
			</li>
            <li Class="CompProperties_Flickable" />
            <li Class="CompProperties_Breakdownable" />
        </comps>
    </ThingDef>

    <ThingDef ParentName="BuildingBase">
        <defName>AC_SleeveCasket</defName>
        <label>sleeve casket</label>
        <description>An ultra-tech casket used for storing grown sleeves before their stack is installed. It uses crypto tech technology to suspend the needs of the sleeves body, while still allowing for the installation of implants or bionics.</description>
        <graphicData>
            <texPath>Things/Building/Misc/SleeveCasket</texPath>
            <graphicClass>Graphic_Multi</graphicClass>
            <shaderType>CutoutComplex</shaderType>
            <drawSize>(2,2)</drawSize>
        </graphicData>
        <castEdgeShadows>True</castEdgeShadows>
        <statBases>
            <MaxHitPoints>150</MaxHitPoints>
            <WorkToBuild>2800</WorkToBuild>
            <Mass>35</Mass>
            <Flammability>1.0</Flammability>
            <Comfort>0.80</Comfort>
            <ImmunityGainSpeedFactor>1.11</ImmunityGainSpeedFactor>
            <MedicalTendQualityOffset>0.9</MedicalTendQualityOffset>
            <SurgerySuccessChanceFactor>3.5</SurgerySuccessChanceFactor>
        </statBases>
		<designationCategory>Misc</designationCategory>
        <size>(1,2)</size>
        <costList>
            <Steel>80</Steel>
            <ComponentIndustrial>5</ComponentIndustrial>
        </costList>
        <building>
            <bed_showSleeperBody>true</bed_showSleeperBody>
            <bed_healPerDay>25</bed_healPerDay>
            <bed_defaultMedical>true</bed_defaultMedical>
        </building>
        <fillPercent>0.4</fillPercent>
        <pathCost>60</pathCost>
        <leaveResourcesWhenKilled>True</leaveResourcesWhenKilled>
        <staticSunShadowHeight>0.17</staticSunShadowHeight>
        <constructionSkillPrerequisite>8</constructionSkillPrerequisite>
        <techLevel>Ultra</techLevel>
        <uiIconScale>0.90</uiIconScale>
		<researchPrerequisites>
		  <li>AC_SleeveProduction</li>
		</researchPrerequisites>
        <comps>
            <li Class="CompProperties_Power">
                <compClass>CompPowerTrader</compClass>
                <shortCircuitInRain>true</shortCircuitInRain>
                <basePowerConsumption>500</basePowerConsumption>
            </li>
            <li Class="CompProperties_Flickable" />
            <li Class="CompProperties_Breakdownable" />      
			<li Class="CompProperties_Forbiddable"/>
        </comps>
    </ThingDef>

</Defs>